AUTHORS
MANIFEST.in
README.creole
setup.py
PyRM.egg-info/PKG-INFO
PyRM.egg-info/SOURCES.txt
PyRM.egg-info/dependency_links.txt
PyRM.egg-info/not-zip-safe
PyRM.egg-info/top_level.txt
pyrm/__init__.py
pyrm/app_settings.py
pyrm/context_processors.py
pyrm/e-rechnung.py
pyrm/index.py
pyrm/kontieren.py
pyrm/manage.py
pyrm/urls.py
pyrm/PyLucid_stuff/PyLucid_internal_page/bill_detail.html
pyrm/PyLucid_stuff/PyLucid_internal_page/bill_summary.html
pyrm/PyLucid_stuff/PyLucid_internal_page/create_bill.css
pyrm/PyLucid_stuff/PyLucid_internal_page/create_bill.html
pyrm/PyLucid_stuff/PyLucid_internal_page/create_bill_tinymce.js
pyrm/admin/__init__.py
pyrm/admin/rechnung.py
pyrm/admin/stammdaten.py
pyrm/django_addons/__init__.py
pyrm/django_addons/forms_addons.py
pyrm/importer/CAO_view.py
pyrm/importer/MMS_view.py
pyrm/importer/__init__.py
pyrm/importer/conbank.py
pyrm/importer/menu.py
pyrm/management/__init__.py
pyrm/management/commands/__init__.py
pyrm/management/commands/import_KRB_buchungen.py
pyrm/management/commands/import_KRB_kunde.py
pyrm/management/commands/import_cronbank.py
pyrm/models/__init__.py
pyrm/models/base_models.py
pyrm/models/rechnung.py
pyrm/models/stammdaten.py
pyrm/static/pyrm/base.css
pyrm/static/pyrm/pyrm_js_tools.js
pyrm/static/pyrm/save_me_genie.js
pyrm/static/pyrm/blueprint/grid.css
pyrm/static/pyrm/html_print/rechnung.css
pyrm/templates/admin/base_site.html
pyrm/templates/import/menu.html
pyrm/templates/import/output.html
pyrm/templates/import/sub_menu.html
pyrm/templates/pyrm/cronbank_import.html
pyrm/templates/pyrm/e-rechnung.html
pyrm/templates/pyrm/e-rechnung_specify.html
pyrm/templates/pyrm/kontieren_select.html
pyrm/templates/pyrm/login.html
pyrm/templates/pyrm/main_menu.html
pyrm/templates/pyrm/admin/print_link.html
pyrm/templates/pyrm/html_print/ci_address.html
pyrm/templates/pyrm/html_print/footer.html
pyrm/templates/pyrm/html_print/rechnung.html
pyrm/templates/pyrm/html_print/rechnung_body.html
pyrm/templates/pyrm/includes/quick_links.html
pyrm/utils/__init__.py
pyrm/utils/csv_utils.py
pyrm/utils/django_modeladmin.py
pyrm/utils/unicode_stringio.py
pyrm/views/__init__.py
