Metadata-Version: 1.0
Name: PyRM
Version: 0.1.0.0812
Summary: PyRM is an open-source "Rechnungs-Manager" using django.
Home-page: http://www.PyRM.org
Author: Jens Diemer
Author-email: UNKNOWN
License: UNKNOWN
Platform: UNKNOWN
Classifier: Development Status :: 1 - Planning
Classifier: Development Status :: 2 - Pre-Alpha
Classifier: Environment :: Web Environment
Classifier: Intended Audience :: Developers
Classifier: License :: OSI Approved :: GNU General Public License (GPL)
Classifier: Programming Language :: Python
Classifier: Programming Language :: JavaScript
Classifier: Framework :: Django
Classifier: Topic :: Database :: Front-Ends
Classifier: Topic :: Documentation
Classifier: Topic :: Internet :: WWW/HTTP :: Dynamic Content
Classifier: Topic :: Internet :: WWW/HTTP :: Site Management
Classifier: Topic :: Internet :: WWW/HTTP :: WSGI :: Application
Classifier: Operating System :: OS Independent
